XinxiguanliZhuanyePythonJiaocheng/README.md
XinxiguanliZhuanyePythonJiaocheng/__init__.py
XinxiguanliZhuanyePythonJiaocheng/__main__.py
XinxiguanliZhuanyePythonJiaocheng/file.epub
XinxiguanliZhuanyePythonJiaocheng/index.html
XinxiguanliZhuanyePythonJiaocheng/css/__init__.py
XinxiguanliZhuanyePythonJiaocheng/css/annotations.css
XinxiguanliZhuanyePythonJiaocheng/css/main.css
XinxiguanliZhuanyePythonJiaocheng/css/normalize.css
XinxiguanliZhuanyePythonJiaocheng/css/popup.css
XinxiguanliZhuanyePythonJiaocheng/font/__init__.py
XinxiguanliZhuanyePythonJiaocheng/font/fontello.eot
XinxiguanliZhuanyePythonJiaocheng/font/fontello.svg
XinxiguanliZhuanyePythonJiaocheng/font/fontello.ttf
XinxiguanliZhuanyePythonJiaocheng/font/fontello.woff
XinxiguanliZhuanyePythonJiaocheng/img/__init__.py
XinxiguanliZhuanyePythonJiaocheng/img/annotator-glyph-sprite.png
XinxiguanliZhuanyePythonJiaocheng/img/annotator-icon-sprite.png
XinxiguanliZhuanyePythonJiaocheng/img/apple-touch-icon.png
XinxiguanliZhuanyePythonJiaocheng/img/cancelfullscreen.png
XinxiguanliZhuanyePythonJiaocheng/img/close.png
XinxiguanliZhuanyePythonJiaocheng/img/fullscreen.png
XinxiguanliZhuanyePythonJiaocheng/img/loader.gif
XinxiguanliZhuanyePythonJiaocheng/img/menu-icon.png
XinxiguanliZhuanyePythonJiaocheng/img/save.png
XinxiguanliZhuanyePythonJiaocheng/img/saved.png
XinxiguanliZhuanyePythonJiaocheng/img/settings-s.png
XinxiguanliZhuanyePythonJiaocheng/img/settings.png
XinxiguanliZhuanyePythonJiaocheng/img/star.png
XinxiguanliZhuanyePythonJiaocheng/js/__init__.py
XinxiguanliZhuanyePythonJiaocheng/js/epub.js
XinxiguanliZhuanyePythonJiaocheng/js/epub.min.js
XinxiguanliZhuanyePythonJiaocheng/js/epub.min.map
XinxiguanliZhuanyePythonJiaocheng/js/hooks.min.js
XinxiguanliZhuanyePythonJiaocheng/js/hooks.min.map
XinxiguanliZhuanyePythonJiaocheng/js/reader.js
XinxiguanliZhuanyePythonJiaocheng/js/reader.js.map
XinxiguanliZhuanyePythonJiaocheng/js/reader.min.js
XinxiguanliZhuanyePythonJiaocheng/js/reader.min.map
xinxiguanli_zhuanye_python_jiaocheng-2024.3.3.0.dist-info/METADATA
xinxiguanli_zhuanye_python_jiaocheng-2024.3.3.0.dist-info/WHEEL
xinxiguanli_zhuanye_python_jiaocheng-2024.3.3.0.dist-info/entry_points.txt
xinxiguanli_zhuanye_python_jiaocheng-2024.3.3.0.dist-info/top_level.txt
xinxiguanli_zhuanye_python_jiaocheng-2024.3.3.0.dist-info/RECORD
